Workbook
Name annual: 'Control Panel V2'!$B$13
Name annualtax: 'Control Panel V2'!$B$16
Name fixcost: 'Control Panel V2'!$B$7
Name float: 'Control Panel V2'!$B$9
Name hourly: 'Control Panel V2'!$B$15
Name monthly: 'Control Panel V2'!$B$14
Name monthlytax: 'Control Panel V2'!$B$18
Name savings: 'Control Panel V2'!$B$24
Name savings_percent: 'Control Panel V2'!$B$25
Name Slicer_Year1: #N/A
Name varycost: 'Control Panel V2'!$B$8

Sheet Control Panel
A1: Control Panel
B2: Value | C2: Decimal Value (Automatic)
A3: Tax Rate (%) | B3: 0.12 | C3: =B3 -> 0.12
A4: Savings Rate (%) | B4: 0.25 | C4: =B4 -> 0.25
A5: Monthly Income Lower Bound | B5: 3500 | C5: =B5 -> 3500
A6: Monthly Income Upper Bound | B6: 4500 | C6: =B6 -> 4500
A7: Monthly Expense Average | B7: 2500 | C7: =B7 -> 2500

Sheet Yearly Saving Result
A1: Tax Rate = | B1: ='Control Panel'!B3 -> 0.12 | C1: Savings Rate = | D1: ='Control Panel'!B4 -> 0.25 | E1: Monthly Lower Bound = | F1: ='Control Panel'!B5 -> 3500 | G1: Monthly Upper Bound = | H1: ='Control Panel'!B6 -> 4500 | I1: Monthly Expense Average= | J1: ='Control Panel'!B7 -> 2500
A2: Year | B2: Month | C2: Date | D2: Gross Pay | E2: Net Pay | F2: Savings | G2: Monthly Expenses (Fixed Costs) | H2: Disposable Income | I2: Within Budget?
A3: 2023 | B3: January | C3: =DATE(A3, 1, 1) -> 44927 | D3: =RANDBETWEEN(F$1,H$1) -> 4140 | E3: =D3*(1 - B$1) -> 3643.2 | F3: =E3*D$1 -> 910.8 | G3: =_xlfn.NORM.INV(RAND(), J$1, J$1/3) -> 3327.5548 | H3: =E3-F3-G3 -> -595.15484 | I3: =IF(H3 > 0, "Good", "Bad") -> Bad
A4: 2023 | B4: February | C4: =EDATE(C3, 1) -> 44958 | D4: =RANDBETWEEN(F$1,H$1) -> 3983 | E4: =D4*(1 - B$1) -> 3505.04 | F4: =E4*D$1 -> 876.26 | G4: =_xlfn.NORM.INV(RAND(), J$1, J$1/3) -> 3018.9147 | H4: =E4-F4-G4 -> -390.13466 | I4: =IF(H4 > 0, "Good", "Bad") -> Bad
A5: 2023 | B5: March | C5: =EDATE(C4, 1) -> 44986 | D5: =RANDBETWEEN(F$1,H$1) -> 4174 | E5: =D5*(1 - B$1) -> 3673.12 | F5: =E5*D$1 -> 918.28 | G5: =_xlfn.NORM.INV(RAND(), J$1, J$1/3) -> 3551.2458 | H5: =E5-F5-G5 -> -796.40584 | I5: =IF(H5 > 0, "Good", "Bad") -> Bad
A6: 2023 | B6: April | C6: =EDATE(C5, 1) -> 45017 | D6: =RANDBETWEEN(F$1,H$1) -> 3678 | E6: =D6*(1 - B$1) -> 3236.64 | F6: =E6*D$1 -> 809.16 | G6: =_xlfn.NORM.INV(RAND(), J$1, J$1/3) -> 2800.284 | H6: =E6-F6-G6 -> -372.804 | I6: =IF(H6 > 0, "Good", "Bad") -> Bad
A7: 2023 | B7: May | C7: =EDATE(C6, 1) -> 45047 | D7: =RANDBETWEEN(F$1,H$1) -> 4350 | E7: =D7*(1 - B$1) -> 3828 | F7: =E7*D$1 -> 957 | G7: =_xlfn.NORM.INV(RAND(), J$1, J$1/3) -> 2217.2832 | H7: =E7-F7-G7 -> 653.71677 | I7: =IF(H7 > 0, "Good", "Bad") -> Good
A8: 2023 | B8: June | C8: =EDATE(C7, 1) -> 45078 | D8: =RANDBETWEEN(F$1,H$1) -> 3794 | E8: =D8*(1 - B$1) -> 3338.72 | F8: =E8*D$1 -> 834.68 | G8: =_xlfn.NORM.INV(RAND(), J$1, J$1/3) -> 1923.0871 | H8: =E8-F8-G8 -> 580.95289 | I8: =IF(H8 > 0, "Good", "Bad") -> Good
A9: 2023 | B9: July | C9: =EDATE(C8, 1) -> 45108 | D9: =RANDBETWEEN(F$1,H$1) -> 4084 | E9: =D9*(1 - B$1) -> 3593.92 | F9: =E9*D$1 -> 898.48 | G9: =_xlfn.NORM.INV(RAND(), J$1, J$1/3) -> 2652.9182 | H9: =E9-F9-G9 -> 42.521791 | I9: =IF(H9 > 0, "Good", "Bad") -> Good
A10: 2023 | B10: August | C10: =EDATE(C9, 1) -> 45139 | D10: =RANDBETWEEN(F$1,H$1) -> 3996 | E10: =D10*(1 - B$1) -> 3516.48 | F10: =E10*D$1 -> 879.12 | G10: =_xlfn.NORM.INV(RAND(), J$1, J$1/3) -> 3694.7381 | H10: =E10-F10-G10 -> -1057.3781 | I10: =IF(H10 > 0, "Good", "Bad") -> Bad
A11: 2023 | B11: September | C11: =EDATE(C10, 1) -> 45170 | D11: =RANDBETWEEN(F$1,H$1) -> 4408 | E11: =D11*(1 - B$1) -> 3879.04 | F11: =E11*D$1 -> 969.76 | G11: =_xlfn.NORM.INV(RAND(), J$1, J$1/3) -> 1200.0733 | H11: =E11-F11-G11 -> 1709.2067 | I11: =IF(H11 > 0, "Good", "Bad") -> Good
A12: 2023 | B12: October | C12: =EDATE(C11, 1) -> 45200 | D12: =RANDBETWEEN(F$1,H$1) -> 4314 | E12: =D12*(1 - B$1) -> 3796.32 | F12: =E12*D$1 -> 949.08 | G12: =_xlfn.NORM.INV(RAND(), J$1, J$1/3) -> 2615.7049 | H12: =E12-F12-G12 -> 231.53507 | I12: =IF(H12 > 0, "Good", "Bad") -> Good
A13: 2023 | B13: November | C13: =EDATE(C12, 1) -> 45231 | D13: =RANDBETWEEN(F$1,H$1) -> 4490 | E13: =D13*(1 - B$1) -> 3951.2 | F13: =E13*D$1 -> 987.8 | G13: =_xlfn.NORM.INV(RAND(), J$1, J$1/3) -> 1763.558 | H13: =E13-F13-G13 -> 1199.842 | I13: =IF(H13 > 0, "Good", "Bad") -> Good
A14: 2023 | B14: December | C14: =EDATE(C13, 1) -> 45261 | D14: =RANDBETWEEN(F$1,H$1) -> 4367 | E14: =D14*(1 - B$1) -> 3842.96 | F14: =E14*D$1 -> 960.74 | G14: =_xlfn.NORM.INV(RAND(), J$1, J$1/3) -> 1445.4671 | H14: =E14-F14-G14 -> 1436.7529 | I14: =IF(H14 > 0, "Good", "Bad") -> Good
A15: 2024 | B15: January | C15: =EDATE(C14, 1) -> 45292 | D15: =RANDBETWEEN(F$1,H$1) -> 3808 | E15: =D15*(1 - B$1) -> 3351.04 | F15: =E15*D$1 -> 837.76 | G15: =_xlfn.NORM.INV(RAND(), J$1, J$1/3) -> 4060.1254 | H15: =E15-F15-G15 -> -1546.8454 | I15: =IF(H15 > 0, "Good", "Bad") -> Bad
... A38: 2025 | B38: December | C38: =EDATE(C37, 1) -> 45992 | D38: =RANDBETWEEN(F$1,H$1) -> 4065 | E38: =D38*(1 - B$1) -> 3577.2 | F38: =E38*D$1 -> 894.3 | G38: =_xlfn.NORM.INV(RAND(), J$1, J$1/3) -> 2984.8636 | H38: =E38-F38-G38 -> -301.96362 | I38: =IF(H38 > 0, "Good", "Bad") -> Bad
A39: Total | B39: =SUBTOTAL(103,Table13[Month]) -> 12 | D39: =SUBTOTAL(109,Table13[Gross Pay]) -> 49778 | E39: =SUBTOTAL(109,Table13[Net Pay]) -> 43804.64 | F39: =SUBTOTAL(109,Table13[Savings]) -> 10951.16 | G39: =SUBTOTAL(109,Table13[Monthly Expenses (Fixed Costs)]) -> 30210.829 | H39: =SUBTOTAL(109,Table13[Disposable Income]) -> 2642.6506 | I39: =SUBTOTAL(103,Table13[Within Budget?]) -> 12
A40: Top Gross (All) | B40: {=_xlfn.XLOOKUP(MAX(Table13[Gross Pay]), Table13[Gross Pay], Table13[[Year]:[Month]], 0)} -> 2023 | C40: November | D40: =MAX(Table13[Gross Pay]) -> 4490
A41: Top Gross (Filter) | B41: =INDEX(Table13[], MATCH(SUBTOTAL(104, Table13[Gross Pay]), Table13[Gross Pay], 0), 1) -> 2023 | C41: =INDEX(Table13[], MATCH(SUBTOTAL(104, Table13[Gross Pay]), Table13[Gross Pay], 0), 2) -> November | D41: =SUBTOTAL(104, Table13[Gross Pay]) -> 4490

Sheet Control Panel V2
A1: Control Panel | E1: Tax Brackets (BC 2026)
A2: Income Type | B2: Hourly Wage | C2: Salary or Hourly wage | E2: Salary (Annual) | F2: Marginal Tax Rate | G2: Rate Increase
A3: Income $ | B3: 30 | C3: Salary amount or hourly wage amount | E3: 0 | F3: 0 | G3: 0
A4: Hours worked per week (avg) | C4: If empty, 40 hours is assumed | E4: 16453 | F4: 0.1906 | G4: =F4-F3 -> 0.1906
A5: Target Savings | B5: Percent Goal | C5: Percentage or amount you aim to save per MONTH | E5: 50364 | F5: 0.217 | G5: =F5-F4 -> 0.0264
A6: Target Amount/Percent | B6: 12 | C6: If Percent, use whole numbers (7.5 = 7.5%) | E6: 58524 | F6: 0.282 | G6: =F6-F5 -> 0.065
A7: Fixed Monthly Costs | B7: 2500 | C7: Fixed costs, such as rent or bills. | E7: 100729 | F7: 0.31 | G7: =F7-F6 -> 0.028
A8: Varied Monthly Costs (avg) | B8: 1000 | C8: Varying Costs, such as grocceries, dining, or presents
A9: Current Bank Balance | B9: -34343 | C9: Can be negative
A12: Calculations (Automatic)
A13: Annual Salary | B13: =IF($B$2 = "Annual Salary", $B$3, IF($B$2 = "Monthly Salary", $B$3*12, IF($B$2 = "Hourly Wage", IF(ISBLANK($B$4), $B$3*2080, $B$3*$B$4*52), 0))) -> 62400
A14: Monthly Salary | B14: =B13/12 -> 5200
A15: Hourly Rate | B15: =IF(ISBLANK($B$4), $B$13/2080, $B$13/(52*$B$4)) -> 30
A16: Annual Tax Owed | B16: {=SUMPRODUCT(($B$13 > Tax_data[Salary (Annual)]) * ($B$13 - Tax_data[Salary (Annual)])*Tax_data[Rate Increase])} -> 9327.1886
A17: Effective Annual Tax Rate | B17: =annualtax/annual -> 0.14947418
A18: Monthly Tax Owed | B18: =$B$16/12 -> 777.26572
A19: Monthly Effective Tax Rate | B19: =(1+B17)^(1/12) - 1 -> 0.011676359
A21: Monthly Fixed Expenses | B21: =IF(ISBLANK(B7), 0, B7) -> 2500
A22: Monthly Varied Expenses (avg) | B22: =B8 -> 1000
A24: Savings $ per month | B24: =IF($B$5 = "Percent Goal", $B$6*$B$14/100, $B$6) -> 624
A25: Savings % per month | B25: =$B$24/($B$14-$B$18) -> 0.14108919 | C25: This percent calculation is POST tax

Sheet One Year Savings
A1: Monthly Salary | B1: =monthly -> 5200 | C1: Monthly Tax deduction | D1: =monthlytax -> 777.26572 | E1: Monthly Fixed Expenses | F1: ='Control Panel V2'!B21 -> 2500 | G1: Monthly Variable Expenses | H1: ='Control Panel V2'!B22 -> 1000 | I1: Monthly Savings | J1: =savings -> 624
A2: Year | B2: Month | C2: Gross Pay | D2: Net Pay | E2: Savings | F2: Monthly Expenses (Fixed Costs) | G2: Monthly Variable Expenses | H2: Total Expenses | I2: Disposable Income | J2: Net Balance | K2: Within Budget?
A3: 2026 | B3: January | C3: =$B$1 -> 5200 | D3: =C3 - $D$1 -> 4422.7343 | E3: =$J$1 -> 624 | F3: =F$1 -> 2500 | G3: =_xlfn.NORM.INV(RAND(), H$1, H$1/3) -> 517.17274 | H3: =Table132[[#This Row],[Monthly Expenses (Fixed Costs)]]+Table132[[#This Row],[Monthly Variable Expenses]] -> 3017.1727 | I3: =D3-E3-Table132[[#This Row],[Total Expenses]] -> 781.56154 | J3: =float+Table132[[#This Row],[Disposable Income]] -> -33561.438 | K3: =IF(I3 > 0, "Good", "Bad") -> Good
A4: 2026 | B4: February | C4: =$B$1 -> 5200 | D4: =C4 - $D$1 -> 4422.7343 | E4: =$J$1 -> 624 | F4: =F$1 -> 2500 | G4: =_xlfn.NORM.INV(RAND(), H$1, H$1/3) -> 801.95592 | H4: =Table132[[#This Row],[Monthly Expenses (Fixed Costs)]]+Table132[[#This Row],[Monthly Variable Expenses]] -> 3301.9559 | I4: =D4-E4-Table132[[#This Row],[Total Expenses]] -> 496.77836 | J4: =J3+Table132[[#This Row],[Disposable Income]] -> -33064.66 | K4: =IF(I4 > 0, "Good", "Bad") -> Good
A5: 2026 | B5: March | C5: =$B$1 -> 5200 | D5: =C5 - $D$1 -> 4422.7343 | E5: =$J$1 -> 624 | F5: =F$1 -> 2500 | G5: =_xlfn.NORM.INV(RAND(), H$1, H$1/3) -> 851.04133 | H5: =Table132[[#This Row],[Monthly Expenses (Fixed Costs)]]+Table132[[#This Row],[Monthly Variable Expenses]] -> 3351.0413 | I5: =D5-E5-Table132[[#This Row],[Total Expenses]] -> 447.69295 | J5: =J4+Table132[[#This Row],[Disposable Income]] -> -32616.967 | K5: =IF(I5 > 0, "Good", "Bad") -> Good
A6: 2026 | B6: April | C6: =$B$1 -> 5200 | D6: =C6 - $D$1 -> 4422.7343 | E6: =$J$1 -> 624 | F6: =F$1 -> 2500 | G6: =_xlfn.NORM.INV(RAND(), H$1, H$1/3) -> 836.99446 | H6: =Table132[[#This Row],[Monthly Expenses (Fixed Costs)]]+Table132[[#This Row],[Monthly Variable Expenses]] -> 3336.9945 | I6: =D6-E6-Table132[[#This Row],[Total Expenses]] -> 461.73982 | J6: =J5+Table132[[#This Row],[Disposable Income]] -> -32155.227 | K6: =IF(I6 > 0, "Good", "Bad") -> Good
A7: 2026 | B7: May | C7: =$B$1 -> 5200 | D7: =C7 - $D$1 -> 4422.7343 | E7: =$J$1 -> 624 | F7: =F$1 -> 2500 | G7: =_xlfn.NORM.INV(RAND(), H$1, H$1/3) -> 261.87521 | H7: =Table132[[#This Row],[Monthly Expenses (Fixed Costs)]]+Table132[[#This Row],[Monthly Variable Expenses]] -> 2761.8752 | I7: =D7-E7-Table132[[#This Row],[Total Expenses]] -> 1036.8591 | J7: =J6+Table132[[#This Row],[Disposable Income]] -> -31118.368 | K7: =IF(I7 > 0, "Good", "Bad") -> Good
A8: 2026 | B8: June | C8: =$B$1 -> 5200 | D8: =C8 - $D$1 -> 4422.7343 | E8: =$J$1 -> 624 | F8: =F$1 -> 2500 | G8: =_xlfn.NORM.INV(RAND(), H$1, H$1/3) -> 1147.8811 | H8: =Table132[[#This Row],[Monthly Expenses (Fixed Costs)]]+Table132[[#This Row],[Monthly Variable Expenses]] -> 3647.8811 | I8: =D8-E8-Table132[[#This Row],[Total Expenses]] -> 150.85323 | J8: =J7+Table132[[#This Row],[Disposable Income]] -> -30967.515 | K8: =IF(I8 > 0, "Good", "Bad") -> Good
A9: 2026 | B9: July | C9: =$B$1 -> 5200 | D9: =C9 - $D$1 -> 4422.7343 | E9: =$J$1 -> 624 | F9: =F$1 -> 2500 | G9: =_xlfn.NORM.INV(RAND(), H$1, H$1/3) -> 1349.5698 | H9: =Table132[[#This Row],[Monthly Expenses (Fixed Costs)]]+Table132[[#This Row],[Monthly Variable Expenses]] -> 3849.5698 | I9: =D9-E9-Table132[[#This Row],[Total Expenses]] -> -50.835535 | J9: =J8+Table132[[#This Row],[Disposable Income]] -> -31018.351 | K9: =IF(I9 > 0, "Good", "Bad") -> Bad
A10: 2026 | B10: August | C10: =$B$1 -> 5200 | D10: =C10 - $D$1 -> 4422.7343 | E10: =$J$1 -> 624 | F10: =F$1 -> 2500 | G10: =_xlfn.NORM.INV(RAND(), H$1, H$1/3) -> 1122.0118 | H10: =Table132[[#This Row],[Monthly Expenses (Fixed Costs)]]+Table132[[#This Row],[Monthly Variable Expenses]] -> 3622.0118 | I10: =D10-E10-Table132[[#This Row],[Total Expenses]] -> 176.72247 | J10: =J9+Table132[[#This Row],[Disposable Income]] -> -30841.628 | K10: =IF(I10 > 0, "Good", "Bad") -> Good
A11: 2026 | B11: September | C11: =$B$1 -> 5200 | D11: =C11 - $D$1 -> 4422.7343 | E11: =$J$1 -> 624 | F11: =F$1 -> 2500 | G11: =_xlfn.NORM.INV(RAND(), H$1, H$1/3) -> 1535.8748 | H11: =Table132[[#This Row],[Monthly Expenses (Fixed Costs)]]+Table132[[#This Row],[Monthly Variable Expenses]] -> 4035.8748 | I11: =D11-E11-Table132[[#This Row],[Total Expenses]] -> -237.14049 | J11: =J10+Table132[[#This Row],[Disposable Income]] -> -31078.769 | K11: =IF(I11 > 0, "Good", "Bad") -> Bad
A12: 2026 | B12: October | C12: =$B$1 -> 5200 | D12: =C12 - $D$1 -> 4422.7343 | E12: =$J$1 -> 624 | F12: =F$1 -> 2500 | G12: =_xlfn.NORM.INV(RAND(), H$1, H$1/3) -> 870.82203 | H12: =Table132[[#This Row],[Monthly Expenses (Fixed Costs)]]+Table132[[#This Row],[Monthly Variable Expenses]] -> 3370.822 | I12: =D12-E12-Table132[[#This Row],[Total Expenses]] -> 427.91225 | J12: =J11+Table132[[#This Row],[Disposable Income]] -> -30650.856 | K12: =IF(I12 > 0, "Good", "Bad") -> Good
A13: 2026 | B13: November | C13: =$B$1 -> 5200 | D13: =C13 - $D$1 -> 4422.7343 | E13: =$J$1 -> 624 | F13: =F$1 -> 2500 | G13: =_xlfn.NORM.INV(RAND(), H$1, H$1/3) -> 961.06148 | H13: =Table132[[#This Row],[Monthly Expenses (Fixed Costs)]]+Table132[[#This Row],[Monthly Variable Expenses]] -> 3461.0615 | I13: =D13-E13-Table132[[#This Row],[Total Expenses]] -> 337.6728 | J13: =J12+Table132[[#This Row],[Disposable Income]] -> -30313.184 | K13: =IF(I13 > 0, "Good", "Bad") -> Good
A14: 2026 | B14: December | C14: =$B$1 -> 5200 | D14: =C14 - $D$1 -> 4422.7343 | E14: =$J$1 -> 624 | F14: =F$1 -> 2500 | G14: =_xlfn.NORM.INV(RAND(), H$1, H$1/3) -> 919.9272 | H14: =Table132[[#This Row],[Monthly Expenses (Fixed Costs)]]+Table132[[#This Row],[Monthly Variable Expenses]] -> 3419.9272 | I14: =D14-E14-Table132[[#This Row],[Total Expenses]] -> 378.80708 | J14: =J13+Table132[[#This Row],[Disposable Income]] -> -29934.376 | K14: =IF(I14 > 0, "Good", "Bad") -> Good
A15: Total | B15: =SUBTOTAL(103,Table132[Month]) -> 12 | C15: =SUBTOTAL(109,Table132[Gross Pay]) -> 62400 | D15: =SUBTOTAL(109,Table132[Net Pay]) -> 53072.811 | E15: =SUBTOTAL(109,Table132[Savings]) -> 7488 | F15: =SUBTOTAL(109,Table132[Monthly Expenses (Fixed Costs)]) -> 30000 | G15: =SUBTOTAL(109,Table132[Monthly Variable Expenses]) -> 11176.188 | H15: =SUBTOTAL(109,Table132[Total Expenses]) -> 41176.188 | I15: =SUBTOTAL(109,Table132[Disposable Income]) -> 4408.6236 | J15: =IF(Table132[[#Totals],[Disposable Income]] > 0, "Positive", "Negative") -> Positive | K15: =COUNTIF(Table132[Within Budget?], "Good") -> 10
A16: Best month | B16: =_xlfn.XLOOKUP(C$16, Table132[Disposable Income], Table132[Month]) -> May | C16: =MAX(Table132[Disposable Income]) -> 1036.8591

Sheet Tax
A1: Tax Brackets
A2: Salary (Annual) | B2: Marginal Tax Rate | C2: Rate Increase
A3: 0 | B3: 0 | C3: 0
A4: 16453 | B4: 0.1906 | C4: =B4-B3 -> 0.1906
A5: 50364 | B5: 0.217 | C5: =B5-B4 -> 0.0264
A6: 58524 | B6: 0.282 | C6: =B6-B5 -> 0.065
A7: 100729 | B7: 0.31 | C7: =B7-B6 -> 0.028
